{
    "directory": "data/tmp",
    "company": "Collibra",
    "unicorn_year": "2019",
    "industry": "Enterprise software",
    "company_description": "Collibra delivers an end-to-end Data Intelligence platform to accelerate digital business transformation.",
    "founders": "Damien Trog, Felix Van De Maele, Pieter De Leenheer, Stijn Christiaens",
    "number_of_founders": "4",
    "year_founded": "2008",
    "yrs_to_unicorn": "11",
    "hq": "Brussels",
    "female": "0",
    "gen_immigrant": "0",
    "immigrant": "0",
    "heritage": "",
    "ethnicity": "White",
    "graduation_year": "2004",
    "age_@_unicorn": "37",
    "seed_investors": "Brustart, Bi3",
    "solo_founder": "0",
    "serial_founder": "0",
    "stem": "1",
    "degree_studied": "CS",
    "stem_ceo": "1",
    "universities": "Vrije, Sint-Lieven",
    "description": "",
    "embedding_text": "Collibra delivers an end-to-end Data Intelligence platform to accelerate digital business transformation."
}