{
    "directory": "data/tmp",
    "company": "Monzo",
    "unicorn_year": "2018",
    "industry": "Financial services",
    "company_description": "Monzo is a digital bank based in the UK that offers online banking services, including current accounts, savings accounts, and money management tools through its mobile app. ",
    "founders": "Gary Dolman, Jason Bates, Jonas Huckestein, Paul Rippon, Tom Blomfield",
    "number_of_founders": "5",
    "year_founded": "2015",
    "yrs_to_unicorn": "3",
    "hq": "London",
    "female": "0",
    "gen_immigrant": "0",
    "immigrant": "0",
    "heritage": "British",
    "ethnicity": "White",
    "graduation_year": "2007",
    "age_@_unicorn": "42",
    "seed_investors": "Passion Capital, Jeremy Yap, BlueWire Capital",
    "solo_founder": "0",
    "serial_founder": "1",
    "stem": "0",
    "degree_studied": "Accountancy, Biochem, Economics, Law",
    "stem_ceo": "0",
    "universities": "Exeter, Liverpool, Uni of Wolves, Uni of Oxford",
    "description": "",
    "embedding_text": "Monzo is a digital bank based in the UK that offers online banking services, including current accounts, savings accounts, and money management tools through its mobile app. "
}