{
    "directory": "data/tmp",
    "company": "Axiom Space",
    "unicorn_year": "2021",
    "industry": "Industrials",
    "company_description": "Axiom Space is the builder, owner, and operator of the commercial space station modules connected to the International Space Station (ISS). The company's Low Earth Orbit platform access and decades of human spaceflight management experience support the research, testing of exploration-enabling technologies, and in-space manufacturing that creates new opportunities for advanced industries, governments, and educators and enable future human space exploration. Axiom provides universal access to the ISS by carrying out missions for a crew of national and private astronauts as well as for clients in the research and manufacturing sector, enabling space travelers to have access to various space initiatives and foster further possibilities. The company is backed by C5 Capital, TQS Advisors, Declaration Partners, Moelis Dynasty Investments, Washington University in St. Louis, The Venture Collective, Aidenlair Capital, Hemisphere Ventures, and Starbridge Venture Capital. Kam Ghaffarian and Michael Suffredini established the Houston, Texas-headquartered aviation and aerospace company in 2016.",
    "founders": "Kam Ghaffarian, Michael Suffredini",
    "number_of_founders": "2",
    "year_founded": "2016",
    "yrs_to_unicorn": "5",
    "hq": "Houston",
    "female": "0",
    "gen_immigrant": "0",
    "immigrant": "1",
    "heritage": "Iranian",
    "ethnicity": "Asian, White",
    "graduation_year": "1994",
    "age_@_unicorn": "49",
    "seed_investors": "IBX, Capitoria",
    "solo_founder": "0",
    "serial_founder": "1",
    "stem": "0",
    "degree_studied": "Engineering",
    "stem_ceo": "0",
    "universities": "Capitol Technology University/The Catholic University/The George Washington University",
    "description": "",
    "embedding_text": "Axiom Space is the builder, owner, and operator of the commercial space station modules connected to the International Space Station (ISS). The company's Low Earth Orbit platform access and decades of human spaceflight management experience support the research, testing of exploration-enabling technologies, and in-space manufacturing that creates new opportunities for advanced industries, governments, and educators and enable future human space exploration. Axiom provides universal access to the ISS by carrying out missions for a crew of national and private astronauts as well as for clients in the research and manufacturing sector, enabling space travelers to have access to various space initiatives and foster further possibilities. The company is backed by C5 Capital, TQS Advisors, Declaration Partners, Moelis Dynasty Investments, Washington University in St. Louis, The Venture Collective, Aidenlair Capital, Hemisphere Ventures, and Starbridge Venture Capital. Kam Ghaffarian and Michael Suffredini established the Houston, Texas-headquartered aviation and aerospace company in 2016.",
    "embedding": [
        0.0031084183137863874,
        0.0034358699340373278,
        0.04221754148602486,
        0.02953709103167057,
        0.04097733646631241,
        -0.007681668736040592,
        -0.02014697901904583,
        0.018261363729834557,
        0.07147622108459473,
        -0.022665351629257202,
        -0.00901045836508274,
        -0.06099776551127434,
        -0.0453813262283802,
        -0.055227022618055344,
        -0.0247914157807827,
        0.033991701900959015,
        0.01033924799412489,
        -0.04130636900663376,
        -0.03115694969892502,
        -0.003293499583378434,
        -0.045102912932634354,
        0.033991701900959015,
        -0.02334873005747795,
        0.0006363161373883486,
        -0.012984171509742737,
        -0.03232122212648392,
        -0.03687707334756851,
        0.03771230950951576,
        0.002243123250082135,
        -0.021931353956460953,
        0.07233677059412003,
        -0.017021160572767258,
        -0.0027335097547620535,
        0.06023845821619034,
        -0.03692769259214401,
        0.034675076603889465,
        -0.03103039786219597,
        0.005217080470174551,
        0.04072423279285431,
        -0.0257278960198164,
        -0.0119654331356287,
        0.01032659225165844,
        0.006586999166756868,
        -0.0127880172803998,
        -0.03799072280526161,
        -0.017514711245894432,
        -0.0460393913090229,
        0.02994205616414547,
        -0.0027714751195162535,
        0.006371861789375544,
        -0.021045494824647903,
        0.003843998070806265,
        0.03877534344792366,
        0.007637375500053167,
        -0.01840057037770748,
        -0.05006372556090355,
        -0.004090773407369852,
        0.033561427146196365,
        -0.017021160572767258,
        0.04133167862892151,
        -0.007017273921519518,
        -0.01669212616980076,
        0.011971760541200638,
        0.06960325688123703,
        0.00792844407260418,
        0.05330343917012215,
        0.03039764054119587,
        0.02979019470512867,
        -0.0247661042958498,
        0.021539045497775078,
        0.012066674418747425,
        0.025715239346027374,
        0.006207345053553581,
        0.021792147308588028,
        -0.014781201258301735,
        -0.044470153748989105,
        -0.013376480899751186,
        0.05811239406466484,
        0.054973918944597244,
        -0.02027353085577488,
        -0.010548057034611702,
        0.02166559547185898,
        0.04021802917122841,
        -0.018590398132801056,
        0.014819166623055935,
        0.005479674786329269,
        0.019881222397089005,
        0.0022858341690152884,
        -0.018641017377376556,
        0.011433917097747326,
        0.027411028742790222,
        0.009118027053773403,
        0.021184701472520828,
        -0.01041517872363329,
        0.06656602770090103,
        0.017805779352784157,
        0.017375504598021507,
        -0.018261363729834557,
        0.03705424442887306,
        0.008643459528684616,
        -0.02930929884314537,
        -0.04054706171154976,
        -0.04120513051748276,
        0.010636643506586552,
        0.017122400924563408,
        0.010231679305434227,
        0.017362849786877632,
        0.007738616783171892,
        0.05821363255381584,
        -0.011301037855446339,
        -0.06155459210276604,
        -0.026221444830298424,
        -0.005764415487647057,
        -0.0009064242476597428,
        -0.034725699573755264,
        -0.04044581949710846,
        -0.007972736842930317,
        -0.014895097352564335,
        0.013186654075980186,
        0.025209033861756325,
        0.02365245297551155,
        0.005568260792642832,
        0.0017005341360345483,
        0.03158722445368767,
        0.03963589295744896,
        -0.06054218113422394,
        -0.03196687996387482,
        -0.01531271729618311,
        -0.054062750190496445,
        -0.0038946187123656273,
        0.02865123189985752,
        -0.02567727491259575,
        0.027689442038536072,
        -0.022728627547621727,
        -0.0238296240568161,
        -0.02339934930205345,
        -0.06049155816435814,
        -0.03692769259214401,
        0.01460402924567461,
        -0.007618392817676067,
        0.026018964126706123,
        -0.016439024358987808,
        0.045431945472955704,
        -0.022893143817782402,
        -0.010940366424620152,
        0.0023601832799613476,
        0.010041851550340652,
        0.0028553155716508627,
        -0.0244623813778162,
        0.016983194276690483,
        -0.026170825585722923,
        0.0029976856894791126,
        0.02085566706955433,
        0.012054018676280975,
        0.0013359079603105783,
        -0.01580626703798771,
        -0.03065074421465397,
        0.017248952761292458,
        0.001790701993741095,
        0.0016261852579191327,
        -0.033485494554042816,
        0.026702340692281723,
        0.020058393478393555,
        0.0006810046033933759,
        -0.02027353085577488,
        0.06499678641557693,
        -0.02458893321454525,
        -0.06246576085686684,
        -0.09126885235309601,
        -0.06641416251659393,
        -0.03675052151083946,
        -0.06378189474344254,
        -0.0976470410823822,
        0.04102795571088791,
        0.001223593601025641,
        -0.017198331654071808,
        -0.015970783308148384,
        0.007960082031786442,
        -0.0515570305287838,
        -0.032827429473400116,
        0.005941587034612894,
        -0.02512044832110405,
        0.02979019470512867,
        -0.04581160098314285,
        -0.04148354381322861,
        -0.002376002026721835,
        -0.06600920110940933,
        0.00721975602209568,
        0.043888017535209656,
        0.016881953924894333,
        -0.0025072991847991943,
        0.022640042006969452,
        0.017729848623275757,
        0.03216936066746712,
        0.013857375830411911,
        -0.014072513207793236,
        -0.04272374510765076,
        -0.0011737640015780926,
        0.043913327157497406,
        0.0007806638022884727,
        0.02448769100010395,
        -0.027588199824094772,
        0.02824626863002777,
        -0.009687508456408978,
        0.0037079553585499525,
        0.016426369547843933,
        0.03702893480658531,
        0.03829444572329521,
        0.016325127333402634,
        -0.00747918663546443,
        0.03027109056711197,
        -0.017818434163928032,
        0.012705758213996887,
        0.026398617774248123,
        -0.019552187994122505,
        -0.005758087616413832,
        0.005514476448297501,
        0.02966364286839962,
        -0.005119003355503082,
        0.05082303285598755,
        -0.06818588078022003,
        0.0465455986559391,
        -0.004457772243767977,
        0.005476511083543301,
        -0.009130681864917278,
        0.04204036667943001,
        -0.009674852713942528,
        -0.006131414324045181,
        0.05254413187503815,
        -0.008599165827035904,
        -0.0008502670680172741,
        0.04778579995036125,
        -0.03156191483139992,
        -0.01492040790617466,
        -0.0474061481654644,
        -0.020969564095139503,
        0.021842768415808678,
        -0.018362605944275856,
        -0.006118759047240019,
        0.0017084436258301139,
        -0.013629583641886711,
        -0.018008261919021606,
        0.03632024675607681,
        0.0462418757379055,
        0.005217080470174551,
        -0.027613511309027672,
        0.007365290075540543,
        -0.06008659303188324,
        0.0258038267493248,
        0.007694324012845755,
        0.01802091673016548,
        0.02339934930205345,
        0.006327569019049406,
        0.00987100787460804,
        -0.006362370681017637,
        -0.04057237133383751,
        -0.00939011201262474,
        0.022956419736146927,
        0.010839126072824001,
        -0.017388159409165382,
        0.00034524797229096293,
        0.01779312454164028,
        -0.0006663721287623048,
        0.02075442671775818,
        -0.035155974328517914,
        0.01631247252225876,
        0.012338759377598763,
        -0.006261129397898912,
        0.021931353956460953,
        -0.01593281887471676,
        -0.06590795516967773,
        -0.004084445536136627,
        0.01479385606944561,
        -0.03705424442887306,
        -0.008415666408836842,
        0.034447286278009415,
        0.002058041747659445,
        -0.008073978126049042,
        -0.05689749866724014,
        0.03930685669183731,
        0.002154537243768573,
        -0.014654649421572685,
        0.026272065937519073,
        0.012148932553827763,
        -0.01533802691847086,
        0.010548057034611702,
        0.03988899290561676,
        0.008826958946883678,
        -0.033308323472738266,
        -0.007251393981277943,
        0.07522214204072952,
        0.010959349572658539,
        -0.018311984837055206,
        0.026120204478502274,
        0.01441420242190361,
        -0.010902401059865952,
        -0.01548988837748766,
        -0.03826913610100746,
        -0.008744699880480766,
        -2.016912549152039e-05,
        0.05699874088168144,
        0.0495322085916996,
        0.03308052942156792,
        -0.06201017647981644,
        -0.016451679170131683,
        0.044014569371938705,
        0.010294954292476177,
        0.06449057906866074,
        0.013515687547624111,
        0.02327279932796955,
        0.02128594182431698,
        0.00594475120306015,
        0.015249441377818584,
        -0.008542218245565891,
        -0.03158722445368767,
        -0.04105326905846596,
        -0.013566307723522186,
        -0.005467019509524107,
        -0.013553652912378311,
        0.003284008242189884,
        -0.01913456805050373,
        -0.04100264608860016,
        0.005644191522151232,
        -0.04763393849134445,
        0.018236054107546806,
        -0.04221754148602486,
        0.02019760012626648,
        0.011516175232827663,
        -0.06580671668052673,
        0.00465709064155817,
        0.027790682390332222,
        -0.03687707334756851,
        0.026550479233264923,
        0.0005750178243033588,
        0.0030024314764887094,
        0.010219023562967777,
        0.05831487476825714,
        -0.011231434531509876,
        0.034953489899635315,
        -0.016666816547513008,
        -0.02913212776184082,
        -0.0026322687044739723,
        -0.035155974328517914,
        0.043837398290634155,
        -0.00766901345923543,
        0.033662665635347366,
        0.006726205814629793,
        -0.010484782047569752,
        0.01824870891869068,
        0.03176439553499222,
        -0.018463846296072006,
        -0.008921871893107891,
        -0.01913456805050373,
        -0.012718413956463337,
        0.008403011597692966,
        -0.03014453873038292,
        0.05679626017808914,
        -0.05056993290781975,
        -0.06428810209035873,
        0.024019451811909676,
        -0.05122799798846245,
        0.007605738006532192,
        0.03685175999999046,
        0.010421506129205227,
        0.022475525736808777,
        0.0020469685550779104,
        -0.005353123415261507,
        0.01974201574921608,
        -0.018666328862309456,
        -0.02981550432741642,
        0.05993473157286644,
        0.026575788855552673,
        -0.006466775666922331,
        -0.044697947800159454,
        0.025386206805706024,
        0.002502553630620241,
        0.04168602451682091,
        0.01626185141503811,
        -0.0016815514536574483,
        0.013098067604005337,
        0.07866434007883072,
        -0.0049038659781217575,
        -0.00458115991204977,
        0.027335098013281822,
        -0.004837426356971264,
        0.0229943860322237,
        0.012224863283336163,
        -0.03295397758483887,
        -0.02519637905061245,
        0.008548545651137829,
        -0.002635432407259941,
        -0.0027477468829602003,
        0.003942075651139021,
        -0.0018286674749106169,
        -0.003249206580221653,
        -0.03128350153565407,
        0.014768545515835285,
        0.04181257635354996,
        0.03249839320778847,
        -0.02923336811363697,
        0.002850569784641266,
        -0.019223153591156006,
        -0.02057725377380848,
        -0.02024822123348713,
        -0.0054227267391979694,
        -0.03184032812714577,
        -0.01931174099445343,
        0.007302014622837305,
        -0.021564355120062828,
        -0.0024946441408246756,
        0.054012127220630646,
        -0.06980574131011963,
        0.05578384920954704,
        0.03571280092000961,
        0.02136187255382538,
        0.04231877997517586,
        -0.0019409817177802324,
        -0.02827157825231552,
        -9.733580372994766e-05,
        0.0926356092095375,
        -0.010396195575594902,
        0.011414933949708939,
        0.024146003648638725,
        -0.08230901509523392,
        -0.008092960342764854,
        0.05117737874388695,
        0.006599654443562031,
        -0.04191381856799126,
        0.014047202654182911,
        -0.006517395842820406,
        -0.02095690928399563,
        0.05036744847893715,
        -0.0018587233498692513,
        -0.006599654443562031,
        -0.05244288966059685,
        0.008086632937192917,
        -0.03280211612582207,
        -0.013996582478284836,
        -0.045431945472955704,
        0.033510804176330566,
        -0.02529762126505375,
        -0.013262584805488586,
        -0.006865412462502718,
        -0.033004600554704666,
        -0.00697298115119338,
        -0.00446726381778717,
        0.006251638289541006,
        0.010782177560031414,
        -0.013692859560251236,
        0.017704537138342857,
        0.026626409962773323,
        -0.025765860453248024,
        0.008137254044413567,
        0.03196687996387482,
        -0.05234165117144585,
        -0.035763420164585114,
        0.0124589828774333,
        0.011022625491023064,
        0.013528342358767986,
        -0.0009246160043403506,
        -0.044343601912260056,
        -0.006441465113312006,
        -0.005293011199682951,
        -0.013528342358767986,
        -0.010972004383802414,
        0.002067533088847995,
        -0.025917721912264824,
        0.012110967189073563,
        0.004366022534668446,
        0.04036989063024521,
        -0.008991475217044353,
        -0.03006860800087452,
        0.05877045914530754,
        -0.009345819242298603,
        -0.026752961799502373,
        -0.022348973900079727,
        0.0245383121073246,
        0.01460402924567461,
        0.010826470330357552,
        0.04204036667943001,
        0.003869308391585946,
        0.0028869532980024815,
        -0.06443995982408524,
        0.0476086288690567,
        0.011174486950039864,
        0.02070380561053753,
        -0.04042050987482071,
        0.005324649158865213,
        -0.050645861774683,
        0.005448036827147007,
        -0.026474548503756523,
        0.013363826088607311,
        0.025183724239468575,
        -0.013515687547624111,
        0.05077241361141205,
        -0.005549278110265732,
        -0.007434893399477005,
        -0.026702340692281723,
        -0.020564598962664604,
        -0.014857131987810135,
        0.03070136532187462,
        -0.008067650720477104,
        -0.015970783308148384,
        0.05117737874388695,
        -0.003302990924566984,
        0.0009000966674648225,
        -0.0020517143420875072,
        0.008478942327201366,
        -0.0035212922375649214,
        0.035257212817668915,
        -0.024070072919130325,
        -0.013503031805157661,
        0.02811971679329872,
        -0.006466775666922331,
        -0.01857774332165718,
        0.009927955456078053,
        0.054670196026563644,
        0.026752961799502373,
        0.006865412462502718,
        0.015996094793081284,
        -0.00761206541210413,
        0.0001077664055628702,
        0.02971426397562027,
        0.03705424442887306,
        -0.011794588528573513,
        0.03103039786219597,
        -0.05148110166192055,
        -0.03816789761185646,
        -0.0252470001578331,
        0.016363093629479408,
        -0.0011595269897952676,
        -0.027790682390332222,
        -0.025259654968976974,
        0.013034791685640812,
        0.021602319553494453,
        -0.017970295622944832,
        -0.019881222397089005,
        -0.01961546391248703,
        0.0025468464009463787,
        -0.008713062852621078,
        -0.019071292132139206,
        0.007624720688909292,
        -0.005024089943617582,
        0.013718169182538986,
        0.008339735679328442,
        0.03801603242754936,
        -0.008770010434091091,
        0.02880309335887432,
        0.0028806256595999002,
        0.08848472684621811,
        0.0017369176493957639,
        -0.011864191852509975,
        0.005796052981168032,
        -0.016907263547182083,
        0.027411028742790222,
        0.03773762285709381,
        -0.01183888129889965,
        0.0009087970829568803,
        0.033333633095026016,
        0.015122889541089535,
        -0.016742747277021408,
        0.022121181711554527,
        -0.016654161736369133,
        -0.004812116269022226,
        0.0127880172803998,
        0.018185433000326157,
        -0.02143780328333378,
        0.0017147711478173733,
        0.00753613468259573,
        -0.011819899082183838,
        -0.0040053511038422585,
        -0.005786561872810125,
        0.022323662415146828,
        0.03718079626560211,
        0.03092915751039982,
        0.0511520691215992,
        -0.012136276811361313,
        -0.0232981089502573,
        0.026930132880806923,
        0.0033188099041581154,
        -0.004359695129096508,
        -0.04768456146121025,
        0.044444844126701355,
        0.042850296944379807,
        -0.02898026630282402,
        0.010737884789705276,
        -0.043584294617176056,
        0.03748451918363571,
        -0.017312228679656982,
        0.06135210767388344,
        -0.00889656227082014,
        0.010143092833459377,
        -0.006454120390117168,
        0.018210742622613907,
        -0.006406663451343775,
        -0.00497346930205822,
        0.05947914719581604,
        0.002020076382905245,
        -0.011560468934476376,
        0.019754670560359955,
        -0.0062231640331447124,
        0.009187630377709866,
        0.0018444863380864263,
        -0.008276459760963917,
        -0.026525169610977173,
        -0.02862592227756977,
        -0.007820875383913517,
        -0.0024028941988945007,
        0.026272065937519073,
        0.0014244939666241407,
        0.020944252610206604,
        -0.005603062454611063,
        -0.016299817711114883,
        0.006941343192011118,
        -0.03234653174877167,
        0.02504451759159565,
        -0.021096114069223404,
        -0.01567971520125866,
        0.053404681384563446,
        -0.006014354061335325,
        -0.011149176396429539,
        0.012129949405789375,
        -0.023412005975842476,
        0.055024538189172745,
        0.009358474053442478,
        0.04206568002700806,
        -0.008491597138345242,
        -0.021273287013173103,
        -0.01548988837748766,
        0.04277436435222626,
        0.04970938339829445,
        0.012920895591378212,
        0.02067849598824978,
        0.024778759106993675,
        -0.03178970515727997,
        0.0021861749701201916,
        -0.003489654278382659,
        0.04153416305780411,
        -0.014667305164039135,
        -0.0061662159860134125,
        0.022209767252206802,
        0.005827690940350294,
        0.02105814963579178,
        -0.01573033630847931,
        0.03591528162360191,
        0.03196687996387482,
        -0.006093448959290981,
        0.023386694490909576,
        -0.0011365895625203848,
        5.961756323813461e-05,
        0.011079573072493076,
        -0.0028742982540279627,
        0.012389379553496838,
        0.033865150064229965,
        0.02575320564210415,
        -0.017919674515724182,
        -0.002750910585746169,
        0.008921871893107891,
        0.02004573866724968,
        0.022855179384350777,
        -0.024880001321434975,
        0.0123830521479249,
        -0.015274751000106335,
        0.002274760976433754,
        -0.005928932223469019,
        0.010902401059865952,
        0.0037522483617067337,
        0.01847650110721588,
        0.007998047396540642,
        0.023234833031892776,
        -0.004540030844509602,
        0.026930132880806923,
        0.015401302836835384,
        0.04244533181190491,
        0.0031416378915309906,
        -0.02019760012626648,
        -0.0060523198917508125,
        -0.005710631143301725,
        0.03181501850485802,
        -0.010661954060196877,
        0.017008505761623383,
        -0.0039104376919567585,
        -0.017223643139004707,
        0.044596705585718155,
        0.022412249818444252,
        -0.009137009270489216,
        0.004473591223359108,
        -0.012199552729725838,
        0.02017229050397873,
        -0.01495837327092886,
        0.009447060525417328,
        0.03723141551017761,
        0.014110478572547436,
        0.013022136874496937,
        -0.002744582947343588,
        -0.04082547500729561,
        0.005558769218623638,
        0.012054018676280975,
        -0.02819564752280712,
        -0.03110632859170437,
        -0.033510804176330566,
        -0.013123378157615662,
        -0.02418396808207035,
        -0.014730580151081085,
        -0.03353611379861832,
        -0.0003632419975474477,
        0.01631247252225876,
        -0.026702340692281723,
        0.03022046945989132,
        0.01928642950952053,
        -0.055530745536088943,
        -0.00796640943735838,
        -0.02817033790051937,
        0.013604273088276386,
        -0.000504228170029819,
        -0.01168701983988285,
        0.0122311906889081,
        -0.00931418128311634,
        -0.031131640076637268,
        -0.01895739696919918,
        -0.02923336811363697,
        0.04879821091890335,
        -0.008833286352455616,
        0.009061078540980816,
        -0.02827157825231552,
        -0.02832219935953617,
        0.004252126440405846,
        0.02332341857254505,
        -0.0037522483617067337,
        0.022538799792528152,
        0.006362370681017637,
        -0.011959105730056763,
        -0.03897782415151596,
        -0.012054018676280975,
        0.027436338365077972,
        0.00404015276581049,
        -0.04849448800086975,
        -0.01467995997518301,
        -0.0014766964595764875,
        0.008599165827035904,
        -0.017248952761292458,
        -0.009092716500163078,
        0.016046714037656784,
        0.017299573868513107,
        0.026246756315231323,
        -0.010801159776747227,
        0.0007842230843380094,
        -0.014616684056818485,
        0.045026980340480804,
        0.020210254937410355,
        0.005527131259441376,
        0.009598921984434128,
        0.028018474578857422,
        -0.004271109122782946,
        0.019552187994122505,
        0.01464199461042881,
        -0.018742259591817856,
        0.02085566706955433,
        0.011547813192009926,
        0.03682645037770271,
        0.002822095761075616,
        0.01490775216370821,
        -0.0120793292298913,
        -0.0025183723773807287,
        -0.015287406742572784,
        -0.0033061548601835966,
        0.009953266009688377,
        -0.004293255507946014,
        0.027486959472298622,
        -0.01445216778665781,
        -0.0004108965222258121,
        0.03247308358550072,
        0.0028806256595999002,
        0.013503031805157661,
        -0.033865150064229965,
        -0.03060012310743332,
        0.008719390258193016,
        -0.05208854749798775,
        0.0031020906753838062,
        -0.017502056434750557,
        0.0010234842775389552,
        0.0009317345102317631,
        -0.04031926766037941,
        0.031207570806145668,
        -0.017147712409496307,
        0.011066918261349201,
        0.019400326535105705,
        0.034877561032772064,
        -0.008656114339828491,
        -0.06383251398801804,
        -0.02590506710112095,
        0.018387915566563606,
        -0.03854754939675331,
        -0.03680114075541496,
        0.015046958811581135,
        -0.022095870226621628,
        0.005416398867964745,
        -0.05689749866724014,
        -0.01490775216370821,
        0.004223652184009552,
        0.010225350968539715,
        0.012870275415480137,
        0.0061662159860134125,
        0.02433582954108715,
        0.0474567674100399,
        0.0499371737241745,
        -0.019223153591156006,
        0.033941078931093216,
        0.0033188099041581154,
        -0.05937790870666504,
        -0.004280600231140852,
        0.009269888512790203,
        0.00772596150636673,
        -0.0239814855158329,
        0.006586999166756868,
        -0.004454608540982008,
        0.012136276811361313,
        -0.0234499704092741,
        -0.013439756818115711,
        -0.03191625699400902,
        0.06175707280635834,
        -0.0032175688538700342,
        -0.022184457629919052,
        -0.008909217081964016,
        0.044495463371276855,
        -0.004353367257863283,
        0.019197843968868256,
        0.0044989013113081455,
        -0.026980753988027573,
        -0.007061567157506943,
        0.03981306403875351,
        -0.033510804176330566,
        0.02880309335887432,
        -0.012060346081852913,
        0.04290091618895531,
        0.002741419244557619,
        -0.0014695778954774141,
        -0.013933306559920311,
        -0.0470011830329895,
        -0.013996582478284836,
        0.011737640015780926,
        0.027360407635569572,
        -0.05041806772351265,
        0.01183888129889965,
        0.007434893399477005,
        0.034396663308143616,
        -0.01041517872363329,
        -0.021247977390885353,
        -0.03892720490694046,
        -0.006064974702894688,
        0.03923092782497406,
        -0.0258038267493248,
        -0.01981794647872448,
        -0.016072025522589684,
        -0.027689442038536072,
        -0.010636643506586552,
        -0.026702340692281723,
        -0.010294954292476177,
        0.013882686384022236,
        -0.015059614554047585,
        0.018894121050834656,
        -0.019906532019376755,
        0.027284476906061172,
        -0.0001958580396603793,
        0.03573811054229736,
        -0.005258210003376007,
        0.0006552988779731095,
        0.021779492497444153,
        0.01905863732099533,
        0.0026417600456625223,
        -0.022146491333842278,
        0.03801603242754936,
        0.004970305599272251,
        0.00456217722967267,
        -0.019223153591156006,
        0.04004085808992386,
        -0.03619369491934776,
        -0.011528830975294113,
        -0.0025863938499242067,
        0.042951539158821106,
        -0.0016008749371394515,
        -0.01646433398127556,
        0.007308342028409243,
        -0.0483173169195652,
        -0.013971271924674511,
        0.03707955405116081,
        -0.013756134547293186,
        0.02814502641558647,
        -0.017704537138342857,
        -0.00491652125492692,
        -0.021779492497444153,
        0.04900069534778595,
        0.02910681627690792,
        0.014768545515835285,
        -0.011997071094810963,
        -0.01918518915772438,
        0.000475358625408262,
        0.03044826164841652,
        -0.0021814294159412384,
        -0.002130808774381876,
        0.015565820038318634,
        -0.011130194179713726,
        0.017299573868513107,
        -0.01638840325176716,
        -0.016881953924894333,
        0.017615951597690582,
        -0.00774494418874383,
        -0.012186897918581963,
        0.0039041100535541773,
        -0.03166315332055092,
        0.02312093786895275,
        -0.004435625858604908,
        0.020640529692173004,
        -0.035485006868839264,
        -0.007757599465548992,
        -4.276052277418785e-05,
        -0.004144557751715183,
        0.01590750925242901,
        0.008928200230002403,
        -0.01013676542788744,
        -0.012914568185806274,
        0.01953953318297863,
        -0.0470011830329895,
        0.008542218245565891,
        -0.017982950434088707,
        -0.011528830975294113,
        0.03011922910809517,
        -0.0024550966918468475,
        0.02946116030216217,
        -0.03799072280526161,
        -0.02105814963579178,
        0.00351496459916234,
        -0.013806755654513836,
        -0.011516175232827663,
        0.005372106097638607,
        -0.016856644302606583,
        -0.010953022167086601,
        0.00838402844965458,
        0.004362858831882477,
        -0.007289359346032143,
        -0.03988899290561676,
        -0.01883084513247013,
        0.0513545498251915,
        0.021703561767935753,
        0.022057905793190002,
        -0.03135943040251732,
        -0.02860061079263687,
        0.03338425233960152,
        0.027588199824094772,
        -0.019425636157393456,
        0.01779312454164028,
        -0.034194182604551315,
        0.013958617113530636,
        -0.034953489899635315,
        -0.022146491333842278,
        -0.05051930993795395,
        0.021564355120062828,
        0.02925867959856987,
        0.0009080061572603881,
        -0.009491353295743465,
        -0.013439756818115711,
        0.023791659623384476,
        -0.02938522957265377,
        -0.02854999154806137,
        0.005830854643136263,
        0.04057237133383751,
        -0.008529562503099442,
        0.004435625858604908,
        -0.01402189303189516,
        -0.011712330393493176,
        -0.03029640018939972,
        0.013427101075649261,
        -0.01605937071144581,
        0.01498368289321661,
        -0.03275149688124657,
        0.010813815519213676,
        0.01626185141503811,
        0.006476266775280237,
        -0.04216691851615906,
        -0.025538068264722824,
        0.032827429473400116,
        0.035611558705568314,
        -0.0250192079693079,
        -0.011547813192009926,
        0.016856644302606583,
        0.007453876081854105,
        0.00936480239033699,
        0.009611576795578003,
        0.02844874933362007,
        0.010105127468705177,
        -0.002587975701317191,
        0.007751272059977055,
        0.0073906006291508675,
        0.01565440557897091,
        -0.01541395764797926,
        -0.007586755324155092,
        0.011307365261018276,
        0.003739593317732215,
        0.012996826320886612,
        0.021488424390554428,
        -0.002232050057500601,
        0.027056684717535973,
        -0.025791171938180923,
        -0.012610845267772675,
        -0.002644923748448491,
        -0.03761107102036476,
        0.018286673352122307,
        -0.033789217472076416,
        0.0008732044952921569,
        -0.014578718692064285,
        -0.0017068617744371295,
        0.022728627547621727,
        -0.020362116396427155,
        0.03237184137105942,
        -0.012180570513010025,
        -0.0015296897618100047,
        -0.013794099912047386,
        -0.035839349031448364,
        -0.027613511309027672,
        0.031131640076637268,
        0.04128105938434601,
        0.01885615475475788,
        0.015173510648310184,
        -0.026651719585061073,
        -0.006118759047240019,
        -0.044723257422447205,
        0.024728139862418175,
        0.02045070193707943,
        0.016704782843589783,
        0.02791723422706127,
        0.008187874220311642,
        -0.010807488113641739,
        0.009927955456078053,
        -0.014895097352564335,
        0.0017052798066288233,
        -0.024601588025689125,
        0.02865123189985752,
        0.010851780883967876,
        0.08504252880811691,
        -0.025436827912926674,
        -0.005387925077229738,
        -0.01455340813845396,
        -0.03632024675607681,
        0.04641904681921005,
        0.05168358236551285,
        -0.0029502289835363626,
        0.007858840748667717,
        -0.013363826088607311,
        -0.007434893399477005,
        0.011712330393493176,
        0.003277680603787303,
        0.025133103132247925,
        -0.013022136874496937,
        -0.005919440649449825,
        -0.007251393981277943,
        -0.032979290932416916,
        -0.007991719990968704,
        -0.02481672540307045,
        0.0511520691215992,
        0.012908240780234337,
        -0.0007423029164783657,
        0.014199065044522285,
        0.02877778373658657,
        0.0026765617076307535,
        0.012819654308259487,
        -0.010554385371506214,
        0.022032594308257103,
        -0.03763638064265251,
        -0.04034458100795746,
        0.00927621591836214,
        -0.005100020673125982,
        0.01455340813845396,
        0.01845119148492813,
        -0.0025183723773807287,
        0.02832219935953617,
        -0.015641750767827034,
        0.01541395764797926,
        -0.011269399896264076,
        0.043609604239463806,
        -0.034826938062906265,
        0.018122157081961632,
        -0.023032350465655327,
        -0.017982950434088707,
        0.0041413940489292145,
        -0.020918942987918854,
        -0.016628852114081383,
        0.011218779720366001,
        0.002086515771225095,
        0.01890677586197853,
        -0.009250905364751816,
        -0.015793612226843834,
        0.018362605944275856,
        0.03680114075541496,
        -0.0127880172803998,
        -0.034472595900297165,
        0.01013676542788744,
        0.02070380561053753,
        -0.0004504438256844878,
        -0.005476511083543301,
        -0.0059732249937951565,
        0.013806755654513836,
        0.02839813008904457,
        -0.03082791529595852,
        -0.01575564593076706,
        -0.035282526165246964,
        -0.0474567674100399,
        0.03986368328332901,
        -0.010370885953307152,
        -0.03882596269249916,
        0.020615220069885254,
        0.01417375449091196,
        -0.0018349949968978763,
        -0.005362614523619413,
        -0.016325127333402634,
        0.009244577959179878,
        -0.011054262518882751,
        0.005400579888373613,
        0.006783153861761093,
        -0.016780713573098183,
        0.018046226352453232,
        -0.021728871390223503,
        -0.022678006440401077,
        -0.008244822733104229,
        0.01037721335887909,
        0.0005164878093637526,
        0.004540030844509602,
        -0.00979507714509964,
        0.022424904629588127,
        0.004138229880481958,
        0.027537580579519272,
        0.004818443674594164,
        0.0029359920881688595,
        0.03796541318297386,
        0.024348486214876175,
        -0.01956484280526638,
        -0.019425636157393456,
        0.002146627753973007,
        -0.033763907849788666,
        -0.009092716500163078,
        0.009510336443781853,
        0.02070380561053753,
        0.015084924176335335,
        -0.01199074275791645,
        0.02923336811363697,
        -0.014224374666810036,
        -0.0026797254104167223,
        -0.01490775216370821,
        0.06570547819137573,
        0.012984171509742737,
        -0.014274995774030685,
        -0.02935991995036602,
        -0.012579207308590412,
        0.0007925280369818211,
        0.0019599644001573324,
        0.011395951732993126,
        -0.010219023562967777,
        0.002500971546396613,
        0.00621050875633955,
        -0.00499245198443532,
        0.00020762335043400526,
        -0.016907263547182083,
        -0.02113408036530018,
        -0.0057612513191998005,
        0.04039520025253296,
        -0.0039484030567109585,
        0.043128710240125656,
        -0.009016785770654678,
        -0.002058041747659445,
        0.01180091593414545,
        0.03173908591270447,
        -0.025816481560468674,
        0.0012251755688339472,
        -0.0014474313938990235,
        0.008567528799176216,
        0.03148598223924637,
        -0.009339491836726665,
        -0.032397154718637466,
        0.0025326095055788755,
        0.03310583904385567,
        -0.044166430830955505,
        -0.006061811000108719,
        0.024399105459451675,
        0.009852024726569653,
        -0.014654649421572685,
        -0.03750982880592346,
        -0.022336319088935852,
        -0.0008819049107842147,
        -0.026550479233264923,
        0.021096114069223404,
        -0.025993652641773224,
        -0.02519637905061245,
        -0.032827429473400116,
        0.006428809836506844,
        0.007510824128985405,
        -0.02781599387526512,
        0.008763683028519154,
        -0.017653917893767357,
        -0.01413578912615776,
        0.01603405922651291,
        0.014426857233047485,
        0.013920651748776436,
        0.012490620836615562,
        -0.018413225188851357,
        0.052797235548496246,
        0.05127861723303795,
        0.01928642950952053,
        0.0019742015283554792,
        -0.005166459828615189,
        -0.01447747740894556,
        -0.022323662415146828,
        0.017210988327860832,
        -0.02560134418308735,
        -0.025436827912926674,
        -0.0063940086401999,
        0.04004085808992386,
        0.013591618277132511,
        -0.004821607377380133,
        -0.017350194975733757,
        0.011446571908891201,
        0.03262494504451752,
        -0.005248718429356813,
        -0.04206568002700806,
        -0.016983194276690483,
        -0.010351902805268764,
        -0.009978576563298702,
        -0.005754923913627863,
        0.020994873717427254,
        -0.0011460809037089348,
        0.01578095741569996,
        0.027537580579519272,
        -0.001972619676962495,
        -0.01056704018265009,
        0.017831088975071907,
        0.02319686859846115,
        0.05922604352235794,
        0.044039878994226456,
        0.01915987953543663,
        0.01646433398127556,
        -0.025613998994231224,
        0.02839813008904457,
        0.000302339147310704,
        0.0020137487445026636,
        0.016552919521927834,
        -0.043862707912921906,
        -0.0119274677708745,
        -0.007327324710786343,
        0.0010598677909001708,
        -0.0040243337862193584,
        -0.0003903319011442363,
        -0.004745676647871733,
        0.019678739830851555,
        -0.02895495481789112,
        -0.04231877997517586,
        -0.03011922910809517,
        0.0129398787394166,
        0.0032175688538700342,
        0.03024577908217907,
        -0.027360407635569572,
        -0.00766901345923543,
        -0.02976488508284092,
        -0.012022380717098713,
        0.010535402223467827,
        -0.02905619703233242,
        -0.0006545078940689564,
        -0.01845119148492813,
        0.011414933949708939,
        0.004229980055242777,
        0.002224140567705035,
        0.0024234589654952288,
        -0.00592576852068305,
        -0.028018474578857422,
        -0.013123378157615662,
        -0.00997224822640419,
        -0.005062055308371782,
        -0.003119491506367922,
        0.05041806772351265,
        0.007339979987591505,
        -0.020792391151189804,
        0.033181771636009216,
        0.043078090995550156,
        -0.013667549006640911,
        0.02100752852857113,
        0.021792147308588028,
        0.00931418128311634,
        0.007903133518993855,
        0.027436338365077972,
        0.022728627547621727,
        -0.07436159253120422,
        0.01852712221443653,
        -0.00951666384935379,
        -0.017248952761292458,
        0.03912968561053276,
        -0.0515570305287838,
        0.004831098951399326,
        -0.012693103402853012,
        -0.010294954292476177,
        0.013654894195497036,
        -0.043381813913583755,
        -0.0023364548105746508,
        0.01172498520463705,
        0.009579939767718315,
        0.012085656635463238,
        0.016831332817673683,
        0.007327324710786343,
        0.01567971520125866,
        -0.03237184137105942,
        0.021868078038096428,
        -0.004366022534668446,
        -0.02047601342201233,
        -0.05892232060432434,
        -0.034092940390110016,
        0.03862348198890686,
        0.01865367405116558,
        -0.014895097352564335,
        0.02903088554739952,
        -0.024778759106993675,
        -0.012243845500051975,
        -0.006504741031676531,
        -0.04814014583826065,
        -0.014237030409276485,
        -0.004590651486068964,
        0.00011409397848183289,
        -0.03115694969892502,
        0.026018964126706123,
        0.017122400924563408,
        -0.013098067604005337,
        -0.007232411298900843,
        -0.0018081028247252107,
        -0.01600874960422516,
        -0.00011261095642112195,
        0.002208321588113904,
        0.0044609359465539455,
        0.010782177560031414,
        -0.011022625491023064,
        0.006454120390117168,
        -0.010630316101014614,
        -0.045102912932634354,
        -0.008599165827035904,
        0.006681913044303656,
        -0.013882686384022236,
        0.02131125144660473,
        0.01883084513247013,
        -0.020513977855443954,
        -0.005476511083543301,
        -0.04242002218961716,
        0.008770010434091091,
        0.0002400521480012685,
        0.02849937044084072,
        -0.026170825585722923,
        0.00407811813056469,
        -0.03001798689365387,
        0.00727670406922698,
        -0.00704891188070178,
        0.011035280302166939,
        0.02065318450331688,
        0.033358942717313766,
        0.01445216778665781,
        0.0017590641509741545,
        -0.015325372107326984,
        0.0123450867831707,
        -0.026196135208010674,
        -0.00759308272972703,
        -0.00349598191678524,
        0.005416398867964745,
        0.05897294357419014,
        0.02953709103167057,
        -0.01471792533993721,
        0.016704782843589783,
        -0.02784130349755287,
        -0.026651719585061073,
        -0.013692859560251236,
        0.007327324710786343,
        0.018514467403292656,
        0.02550010196864605,
        -0.020362116396427155,
        -0.032549016177654266,
        -0.010896073654294014,
        -0.04803890362381935,
        0.021792147308588028,
        0.035333145409822464,
        0.0073336525820195675,
        -0.007827202789485455,
        -0.015970783308148384,
        -0.0239308662712574,
        -0.02979019470512867,
        0.0026385963428765535,
        0.004568504635244608,
        0.021779492497444153,
        -0.027638820931315422,
        0.02804378606379032,
        -0.020969564095139503,
        0.05902356281876564,
        0.007118515204638243,
        0.011433917097747326,
        -0.01588219776749611,
        -0.017982950434088707,
        -0.014388891868293285,
        0.019602809101343155,
        0.034042321145534515,
        -0.016641506925225258,
        -0.0033377925865352154,
        0.03685175999999046,
        -0.023918211460113525,
        -0.017413469031453133,
        -0.017008505761623383,
        -0.01915987953543663,
        0.01852712221443653,
        0.0024329503066837788,
        0.011357986368238926,
        0.014971028082072735,
        -0.004046480171382427,
        -0.018767569214105606,
        0.008257477544248104,
        -0.012718413956463337,
        0.0241586584597826,
        -0.002270015422254801,
        -0.006280112080276012,
        -0.027638820931315422,
        -0.03103039786219597,
        0.018590398132801056,
        -0.006352879106998444,
        0.018046226352453232,
        0.013098067604005337,
        0.012515931390225887,
        0.005856165196746588,
        0.004416643176227808,
        -0.02860061079263687,
        -0.03852223977446556,
        0.003806032706052065,
        0.023665107786655426,
        -0.018944742158055305,
        0.023892899975180626,
        -0.013553652912378311,
        0.0058213635347783566,
        0.00935214664787054,
        0.01565440557897091,
        -0.03029640018939972,
        0.00823216699063778,
        -0.013604273088276386,
        -0.013490376994013786,
        -0.0013683367287740111,
        -0.013844721019268036,
        0.010661954060196877,
        0.02961302176117897,
        0.0045969788916409016,
        0.02781599387526512,
        0.006536378525197506,
        0.0118895024061203,
        -0.01180091593414545,
        0.004944995045661926,
        0.024019451811909676,
        -0.007365290075540543,
        0.0013042701175436378,
        -0.022576766088604927,
        0.004033825360238552,
        -0.0018792880000546575,
        0.008491597138345242,
        0.01610998995602131,
        -0.010554385371506214,
        -0.01974201574921608,
        -0.0006695358897559345,
        0.003072034800425172,
        0.018894121050834656,
        0.033763907849788666,
        0.005650518927723169,
        -0.008770010434091091,
        0.016717437654733658,
        0.02989143505692482,
        0.025664620101451874,
        0.008111943490803242,
        -0.02433582954108715,
        0.052594754844903946,
        0.00695399846881628,
        0.035029422491788864,
        -0.021766837686300278,
        0.003872472094371915,
        0.011997071094810963,
        0.006865412462502718,
        -0.000681400066241622,
        -0.011035280302166939,
        -0.022184457629919052,
        -0.021817456930875778,
        -0.03831975907087326,
        -0.04077485576272011,
        -0.022412249818444252,
        -0.02166559547185898,
        -0.017173022031784058,
        -0.0012971516698598862,
        -0.03295397758483887,
        0.021956663578748703,
        0.01628716289997101,
        -0.00804234016686678,
        0.017565330490469933,
        0.009491353295743465,
        0.003274516901001334,
        -0.005334140732884407,
        0.002587975701317191,
        0.008586511015892029,
        -0.0031606208067387342,
        0.014578718692064285,
        0.04102795571088791,
        0.03237184137105942,
        -0.02872716262936592,
        -0.010959349572658539,
        -0.00723873870447278,
        -0.01183888129889965,
        -0.034826938062906265,
        -0.02862592227756977,
        0.004913357086479664,
        -0.013110722415149212,
        0.03880065307021141,
        -0.006220000330358744,
        -0.014047202654182911,
        -0.004426134284585714,
        0.015603785403072834,
        0.02032415196299553,
        -0.02829688787460327,
        0.03095446713268757,
        -0.025993652641773224,
        0.0462418757379055,
        -0.01895739696919918,
        0.017388159409165382,
        -0.05158234387636185,
        0.018008261919021606,
        0.02865123189985752,
        -0.0236271433532238,
        -0.03680114075541496,
        0.035611558705568314,
        -0.00916231982409954,
        0.026904823258519173,
        0.006941343192011118,
        0.024993896484375,
        0.001104160794056952,
        -0.00970649067312479,
        -0.011680692434310913,
        0.03664927929639816
    ]
}